disk_detective/Controller.py
disk_detective/__init__.py
disk_detective/__main__.py
disk_detective/ext/__init__.py
disk_detective/ext/config/__init__.py
disk_detective/ext/config/ext-file-descriptor-table.json
disk_detective/ext/config/ext-inode.json
disk_detective/ext/config/ext-super-block.json
disk_detective/fat/FATParser.py
disk_detective/fat/FATPrinter.py
disk_detective/fat/__init__.py
disk_detective/fat/config/__init__.py
disk_detective/fat/config/fat-directory-entry.json
disk_detective/fat/config/fat-fs-info.json
disk_detective/fat/config/fat-long-filename.json
disk_detective/fat/config/fat-type.json
disk_detective/fat/config/fat.json
disk_detective/fat/config/fat1216.json
disk_detective/fat/config/fat32.json
disk_detective/mbr/MBRPrinter.py
disk_detective/mbr/MasterBootRecord.py
disk_detective/mbr/PartitionEntry.py
disk_detective/mbr/__init__.py
disk_detective/ntfs/__init__.py
disk_detective/ntfs/config/__init__.py
disk_detective/usage/DiskUsagePrinter.py
disk_detective/usage/__init__.py
disk_detective/util/ConfigLoader.py
disk_detective/util/TestFileCreator.py
disk_detective/util/__init__.py
disk_detective-0.4.0.dist-info/LICENSE.md
disk_detective-0.4.0.dist-info/METADATA
disk_detective-0.4.0.dist-info/WHEEL
disk_detective-0.4.0.dist-info/entry_points.txt
disk_detective-0.4.0.dist-info/top_level.txt
disk_detective-0.4.0.dist-info/RECORD
