Metadata-Version: 2.1
Name: disk-detective
Version: 0.4.0
Summary: Provides tools to analyze disks on byte level
Home-page: https://github.com/5f0ne/disk-detective
Author: 5f0
License: MIT
Classifier: Operating System :: OS Independent 
Classifier: Programming Language :: Python :: 3 
Classifier: License :: OSI Approved :: MIT License 
License-File: LICENSE.md
Requires-Dist: hash-calc (==1.1.0)
Requires-Dist: partitiontypes (==1.0.1)
Requires-Dist: cnvrtr (==1.1.1)
Requires-Dist: ntrprtr (==1.3.2)
